Metadata-Version: 1.0
Name: eji-gaus-bino-distribution
Version: 0.1
Summary: Gaussian and Binomial distributions
Home-page: UNKNOWN
Author: Elijah James Ikpeme
Author-email: ikpemeelijahjames@outlook.com
License: UNKNOWN
Platform: UNKNOWN
